{
  "id": "set_01",
  "title": "Pasalacabra 2026-06-05 · No. 156",
  "questions": [
    {
      "letter": "A",
      "question": "Empieza por A: Dios griego de la música y las artes.",
      "answer": "Apolo"
    },
    {
      "letter": "B",
      "question": "Empieza por B: Nombre romano del dios del vino.",
      "answer": "Baco"
    },
    {
      "letter": "C",
      "question": "Empieza por C: Planeta enano situado en el cinturón principal del Sistema Solar.",
      "answer": "Ceres"
    },
    {
      "letter": "D",
      "question": "Empieza por D: Ninfa que fue transformada en laurel para huir de Apolo.",
      "answer": "Dafne"
    },
    {
      "letter": "E",
      "question": "Empieza por E: Compilación medieval de poemas nórdicos que recoge mitos escandinavos.",
      "answer": "Edda"
    },
    {
      "letter": "F",
      "question": "Empieza por F: Ser mitológico romano con patas de cabra, asociado a los bosques.",
      "answer": "Fauno"
    },
    {
      "letter": "G",
      "question": "Empieza por G: Copa sagrada de la tradición artúrica buscada por los caballeros.",
      "answer": "Grial"
    },
    {
      "letter": "H",
      "question": "Empieza por H: Esposa de Zeus y diosa griega del matrimonio.",
      "answer": "Hera"
    },
    {
      "letter": "I",
      "question": "Empieza por I: Poema épico atribuido a Homero sobre la guerra de Troya.",
      "answer": "Ilíada"
    },
    {
      "letter": "J",
      "question": "Empieza por J: Personaje enmascarado del folclore de Piornal que recibe lanzamientos de nabos.",
      "answer": "Jarramplas"
    },
    {
      "letter": "L",
      "question": "Empieza por L: Deidades domésticas de la antigua Roma.",
      "answer": "Lares"
    },
    {
      "letter": "M",
      "question": "Empieza por M: Diosa romana de la sabiduría, equivalente a Atenea.",
      "answer": "Minerva"
    },
    {
      "letter": "N",
      "question": "Empieza por N: Emperador romano asociado al incendio de Roma en el 64 d. C.",
      "answer": "Nerón"
    },
    {
      "letter": "Ñ",
      "question": "Contiene la Ñ: Estereotipo fílmico que caricaturiza lo castizo en ciertas películas españolas.",
      "answer": "españolada"
    },
    {
      "letter": "O",
      "question": "Empieza por O: Músico mitológico que intentó rescatar a Eurídice del inframundo.",
      "answer": "Orfeo"
    },
    {
      "letter": "P",
      "question": "Empieza por P: Primera mujer en la mitología griega, portadora de una famosa caja.",
      "answer": "Pandora"
    },
    {
      "letter": "Q",
      "question": "Empieza por Q: Divinidad romana identificada con Rómulo tras su apoteosis.",
      "answer": "Quirino"
    },
    {
      "letter": "R",
      "question": "Empieza por R: Madre de Zeus y esposa de Crono en la mitología griega.",
      "answer": "Rea"
    },
    {
      "letter": "S",
      "question": "Empieza por S: Viejo tutor de Dioniso, representado a menudo ebrio.",
      "answer": "Sileno"
    },
    {
      "letter": "T",
      "question": "Empieza por T: Mayor satélite de Saturno, con densa atmósfera.",
      "answer": "Titán"
    },
    {
      "letter": "U",
      "question": "Empieza por U: Héroe de la Odisea célebre por su astucia.",
      "answer": "Ulises"
    },
    {
      "letter": "V",
      "question": "Empieza por V: Dios romano del fuego y la forja, equivalente de Hefesto.",
      "answer": "Vulcano"
    },
    {
      "letter": "X",
      "question": "Contiene la X: Pueblo mesoamericano que fundó Tenochtitlan y hablaba náhuatl.",
      "answer": "mexica"
    },
    {
      "letter": "Y",
      "question": "Empieza por Y: Criatura críptida asociada a las nieves del Himalaya.",
      "answer": "yeti"
    },
    {
      "letter": "Z",
      "question": "Empieza por Z: Protagonista del libro de Nietzsche 'Así habló ...'.",
      "answer": "Zaratustra"
    }
  ]
}
